odoo/addons/event_badge_design/README.rst
odoo/addons/event_badge_design/__init__.py
odoo/addons/event_badge_design/__manifest__.py
odoo/addons/event_badge_design/i18n/event_badge_design.pot
odoo/addons/event_badge_design/readme/CONTRIBUTORS.rst
odoo/addons/event_badge_design/readme/DESCRIPTION.rst
odoo/addons/event_badge_design/static/description/icon.png
odoo/addons/event_badge_design/static/description/index.html
odoo/addons/event_badge_design/views/event_event.xml
odoo14_addon_event_badge_design-14.0.1.0.1.dist-info/METADATA
odoo14_addon_event_badge_design-14.0.1.0.1.dist-info/WHEEL
odoo14_addon_event_badge_design-14.0.1.0.1.dist-info/top_level.txt
odoo14_addon_event_badge_design-14.0.1.0.1.dist-info/RECORD
